[
    {
        "created_at": "Sat Apr 18 12:02:57 +0000 2020",
        "favorite_count": 595520,
        "hashtags": [],
        "id": 1251481340744212481,
        "id_str": "1251481340744212481",
        "lang": "en",
        "media": [
            {
                "display_url": "pic.twitter.com/iQd99vAGbR",
                "expanded_url": "https://twitter.com/Cristiano/status/1251481340744212481/photo/1",
                "id": 1251481335102943233,
                "media_url": "http://pbs.twimg.com/media/EV4npMXXsAEhnXp.jpg",
                "media_url_https": "https://pbs.twimg.com/media/EV4npMXXsAEhnXp.jpg",
                "sizes": {
                    "thumb": {
                        "w": 150,
                        "h": 150,
                        "resize": "crop"
                    },
                    "large": {
                        "w": 1080,
                        "h": 1349,
                        "resize": "fit"
                    },
                    "small": {
                        "w": 544,
                        "h": 680,
                        "resize": "fit"
                    },
                    "medium": {
                        "w": 961,
                        "h": 1200,
                        "resize": "fit"
                    }
                },
                "type": "photo",
                "url": "https://t.co/iQd99vAGbR"
            }
        ],
        "retweet_count": 38094,
        "source": "<a href=\"http://twitter.com/download/iphone\" rel=\"nofollow\">Twitter for iPhone</a>",
        "text": "The best way to start the day \ud83d\ude4f\u2764\ufe0f https://t.co/iQd99vAGbR",
        "urls": [],
        "user": {
            "id": 155659213,
            "id_str": "155659213"
        },
        "user_mentions": []
    },
    {
        "created_at": "Fri Apr 17 18:17:09 +0000 2020",
        "favorite_count": 311805,
        "hashtags": [
            {
                "text": "siiiimmmmm"
            }
        ],
        "id": 1251213121743716353,
        "id_str": "1251213121743716353",
        "lang": "en",
        "media": [
            {
                "display_url": "pic.twitter.com/7Tmmno0tO7",
                "expanded_url": "https://twitter.com/Cristiano/status/1251213121743716353/video/1",
                "id": 1251213097135636481,
                "media_url": "http://pbs.twimg.com/ext_tw_video_thumb/1251213097135636481/pu/img/Fmu6hF-JdAgntBTE.jpg",
                "media_url_https": "https://pbs.twimg.com/ext_tw_video_thumb/1251213097135636481/pu/img/Fmu6hF-JdAgntBTE.jpg",
                "sizes": {
                    "large": {
                        "w": 480,
                        "h": 600,
                        "resize": "fit"
                    },
                    "small": {
                        "w": 480,
                        "h": 600,
                        "resize": "fit"
                    },
                    "thumb": {
                        "w": 150,
                        "h": 150,
                        "resize": "crop"
                    },
                    "medium": {
                        "w": 480,
                        "h": 600,
                        "resize": "fit"
                    }
                },
                "type": "video",
                "url": "https://t.co/7Tmmno0tO7",
                "video_info": {
                    "aspect_ratio": [
                        4,
                        5
                    ],
                    "duration_millis": 18545,
                    "variants": [
                        {
                            "bitrate": 632000,
                            "content_type": "video/mp4",
                            "url": "https://video.twimg.com/ext_tw_video/1251213097135636481/pu/vid/320x400/nS-okkBoaLiYcHVg.mp4?tag=10"
                        },
                        {
                            "bitrate": 832000,
                            "content_type": "video/mp4",
                            "url": "https://video.twimg.com/ext_tw_video/1251213097135636481/pu/vid/360x450/fKzNjgNFQFRPfSkK.mp4?tag=10"
                        },
                        {
                            "content_type": "application/x-mpegURL",
                            "url": "https://video.twimg.com/ext_tw_video/1251213097135636481/pu/pl/8FydWGVXd9ZzVK3V.m3u8?tag=10"
                        },
                        {
                            "bitrate": 2176000,
                            "content_type": "video/mp4",
                            "url": "https://video.twimg.com/ext_tw_video/1251213097135636481/pu/vid/480x600/aM3Ixn_BM37IvWWs.mp4?tag=10"
                        }
                    ]
                }
            }
        ],
        "retweet_count": 30456,
        "source": "<a href=\"http://twitter.com/download/iphone\" rel=\"nofollow\">Twitter for iPhone</a>",
        "text": "Like father like son \ud83d\ude02\ud83d\udc68\u200d\ud83d\udc66\u2764\ufe0f #siiiimmmmm https://t.co/7Tmmno0tO7",
        "urls": [],
        "user": {
            "id": 155659213,
            "id_str": "155659213"
        },
        "user_mentions": []
    },
    {
        "created_at": "Wed Apr 15 19:10:38 +0000 2020",
        "favorite_count": 310981,
        "hashtags": [],
        "id": 1250501806163202051,
        "id_str": "1250501806163202051",
        "lang": "en",
        "media": [
            {
                "display_url": "pic.twitter.com/n2ZIUhGa5d",
                "expanded_url": "https://twitter.com/Cristiano/status/1250501806163202051/photo/1",
                "id": 1250501800085651458,
                "media_url": "http://pbs.twimg.com/media/EVqswwEXgAIy3Xo.jpg",
                "media_url_https": "https://pbs.twimg.com/media/EVqswwEXgAIy3Xo.jpg",
                "sizes": {
                    "thumb": {
                        "w": 150,
                        "h": 150,
                        "resize": "crop"
                    },
                    "small": {
                        "w": 544,
                        "h": 680,
                        "resize": "fit"
                    },
                    "medium": {
                        "w": 960,
                        "h": 1200,
                        "resize": "fit"
                    },
                    "large": {
                        "w": 990,
                        "h": 1237,
                        "resize": "fit"
                    }
                },
                "type": "photo",
                "url": "https://t.co/n2ZIUhGa5d"
            }
        ],
        "retweet_count": 19779,
        "source": "<a href=\"http://twitter.com/download/iphone\" rel=\"nofollow\">Twitter for iPhone</a>",
        "text": "Always challenge yourself! \ud83d\udc4cFor me it's time to study \ud83e\udd13 https://t.co/n2ZIUhGa5d",
        "urls": [],
        "user": {
            "id": 155659213,
            "id_str": "155659213"
        },
        "user_mentions": []
    },
    {
        "created_at": "Sun Apr 12 13:39:28 +0000 2020",
        "favorite_count": 298327,
        "hashtags": [
            {
                "text": "stayhome"
            }
        ],
        "id": 1249331300462481408,
        "id_str": "1249331300462481408",
        "lang": "en",
        "media": [
            {
                "display_url": "pic.twitter.com/DZsSKqYWeb",
                "expanded_url": "https://twitter.com/Cristiano/status/1249331300462481408/photo/1",
                "id": 1249331295026585606,
                "media_url": "http://pbs.twimg.com/media/EVaEMY7WoAYtZSm.jpg",
                "media_url_https": "https://pbs.twimg.com/media/EVaEMY7WoAYtZSm.jpg",
                "sizes": {
                    "medium": {
                        "w": 1080,
                        "h": 810,
                        "resize": "fit"
                    },
                    "thumb": {
                        "w": 150,
                        "h": 150,
                        "resize": "crop"
                    },
                    "large": {
                        "w": 1080,
                        "h": 810,
                        "resize": "fit"
                    },
                    "small": {
                        "w": 680,
                        "h": 510,
                        "resize": "fit"
                    }
                },
                "type": "photo",
                "url": "https://t.co/DZsSKqYWeb"
            }
        ],
        "retweet_count": 17603,
        "source": "<a href=\"http://twitter.com/download/iphone\" rel=\"nofollow\">Twitter for iPhone</a>",
        "text": "We wish a Happy Easter to everyone \ud83c\udf0d\u2764\ufe0f\ud83d\ude4f\n#stayhome https://t.co/DZsSKqYWeb",
        "urls": [],
        "user": {
            "id": 155659213,
            "id_str": "155659213"
        },
        "user_mentions": []
    },
    {
        "created_at": "Sat Apr 11 09:15:41 +0000 2020",
        "favorite_count": 67658,
        "hashtags": [],
        "id": 1248902530068815872,
        "id_str": "1248902530068815872",
        "lang": "en",
        "retweet_count": 5504,
        "source": "<a href=\"http://twitter.com/download/iphone\" rel=\"nofollow\">Twitter for iPhone</a>",
        "text": "Another week of playing inside and staying active. Thanks to everyone for trying to beat me \ud83d\ude09 maybe next time! Over\u2026 https://t.co/HCX4e8fsAR",
        "truncated": true,
        "urls": [
            {
                "expanded_url": "https://twitter.com/i/web/status/1248902530068815872",
                "url": "https://t.co/HCX4e8fsAR"
            }
        ],
        "user": {
            "id": 155659213,
            "id_str": "155659213"
        },
        "user_mentions": []
    },
    {
        "created_at": "Fri Apr 10 19:09:20 +0000 2020",
        "favorite_count": 227091,
        "hashtags": [],
        "id": 1248689538828034048,
        "id_str": "1248689538828034048",
        "lang": "en",
        "retweet_count": 25303,
        "source": "<a href=\"http://twitter.com/download/iphone\" rel=\"nofollow\">Twitter for iPhone</a>",
        "text": "In this very difficult moment for our world it is important we unite and support each other. Let\u2019s all do what we c\u2026 https://t.co/74Bpj1hEx8",
        "truncated": true,
        "urls": [
            {
                "expanded_url": "https://twitter.com/i/web/status/1248689538828034048",
                "url": "https://t.co/74Bpj1hEx8"
            }
        ],
        "user": {
            "id": 155659213,
            "id_str": "155659213"
        },
        "user_mentions": []
    },
    {
        "created_at": "Sat Apr 04 12:43:05 +0000 2020",
        "favorite_count": 354994,
        "hashtags": [
            {
                "text": "stayhomestaysafe"
            }
        ],
        "id": 1246418009758941185,
        "id_str": "1246418009758941185",
        "lang": "en",
        "media": [
            {
                "display_url": "pic.twitter.com/SkPiUwzCxn",
                "expanded_url": "https://twitter.com/Cristiano/status/1246418009758941185/video/1",
                "id": 1246417945221267456,
                "media_url": "http://pbs.twimg.com/ext_tw_video_thumb/1246417945221267456/pu/img/JUktwl28X07-C65b.jpg",
                "media_url_https": "https://pbs.twimg.com/ext_tw_video_thumb/1246417945221267456/pu/img/JUktwl28X07-C65b.jpg",
                "sizes": {
                    "large": {
                        "w": 480,
                        "h": 600,
                        "resize": "fit"
                    },
                    "small": {
                        "w": 480,
                        "h": 600,
                        "resize": "fit"
                    },
                    "thumb": {
                        "w": 150,
                        "h": 150,
                        "resize": "crop"
                    },
                    "medium": {
                        "w": 480,
                        "h": 600,
                        "resize": "fit"
                    }
                },
                "type": "video",
                "url": "https://t.co/SkPiUwzCxn",
                "video_info": {
                    "aspect_ratio": [
                        4,
                        5
                    ],
                    "duration_millis": 18420,
                    "variants": [
                        {
                            "bitrate": 2176000,
                            "content_type": "video/mp4",
                            "url": "https://video.twimg.com/ext_tw_video/1246417945221267456/pu/vid/480x600/1rQ4Sr-X-l1sWhyY.mp4?tag=10"
                        },
                        {
                            "bitrate": 832000,
                            "content_type": "video/mp4",
                            "url": "https://video.twimg.com/ext_tw_video/1246417945221267456/pu/vid/360x450/xZ_9NOGs4PKGg3D3.mp4?tag=10"
                        },
                        {
                            "content_type": "application/x-mpegURL",
                            "url": "https://video.twimg.com/ext_tw_video/1246417945221267456/pu/pl/okSYNbrFTtApSrwi.m3u8?tag=10"
                        },
                        {
                            "bitrate": 632000,
                            "content_type": "video/mp4",
                            "url": "https://video.twimg.com/ext_tw_video/1246417945221267456/pu/vid/320x400/RqymWZD-Iuk7BMp2.mp4?tag=10"
                        }
                    ]
                }
            }
        ],
        "retweet_count": 34708,
        "source": "<a href=\"http://twitter.com/download/iphone\" rel=\"nofollow\">Twitter for iPhone</a>",
        "text": "Stay home and keep stylish \ud83d\udc87\ud83c\udffd\u200d\u2642\ufe0f\ud83d\udc69\u200d\u2764\ufe0f\u200d\ud83d\udc8b\u200d\ud83d\udc68 #stayhomestaysafe https://t.co/SkPiUwzCxn",
        "urls": [],
        "user": {
            "id": 155659213,
            "id_str": "155659213"
        },
        "user_mentions": []
    },
    {
        "created_at": "Wed Apr 01 11:23:13 +0000 2020",
        "favorite_count": 308707,
        "hashtags": [
            {
                "text": "stayhomesavelives"
            }
        ],
        "id": 1245310749045653504,
        "id_str": "1245310749045653504",
        "lang": "en",
        "media": [
            {
                "display_url": "pic.twitter.com/ElschZvXdQ",
                "expanded_url": "https://twitter.com/Cristiano/status/1245310749045653504/photo/1",
                "id": 1245310743349800963,
                "media_url": "http://pbs.twimg.com/media/EUg7hexXsAMF-Gn.jpg",
                "media_url_https": "https://pbs.twimg.com/media/EUg7hexXsAMF-Gn.jpg",
                "sizes": {
                    "small": {
                        "w": 544,
                        "h": 680,
                        "resize": "fit"
                    },
                    "thumb": {
                        "w": 150,
                        "h": 150,
                        "resize": "crop"
                    },
                    "large": {
                        "w": 1080,
                        "h": 1350,
                        "resize": "fit"
                    },
                    "medium": {
                        "w": 960,
                        "h": 1200,
                        "resize": "fit"
                    }
                },
                "type": "photo",
                "url": "https://t.co/ElschZvXdQ"
            }
        ],
        "retweet_count": 23632,
        "source": "<a href=\"http://twitter.com/download/iphone\" rel=\"nofollow\">Twitter for iPhone</a>",
        "text": "Breathe in, breathe out.\ud83e\uddd8\u200d\u2642\ufe0f Stay active\ud83c\udfc3\ud83c\udffb\u200d\u2642\ufe0f #stayhomesavelives https://t.co/ElschZvXdQ",
        "urls": [],
        "user": {
            "id": 155659213,
            "id_str": "155659213"
        },
        "user_mentions": []
    },
    {
        "created_at": "Mon Mar 30 13:02:41 +0000 2020",
        "favorite_count": 244411,
        "hashtags": [],
        "id": 1244611003863580672,
        "id_str": "1244611003863580672",
        "lang": "en",
        "retweet_count": 21926,
        "source": "<a href=\"http://twitter.com/download/iphone\" rel=\"nofollow\">Twitter for iPhone</a>",
        "text": "In this difficult moment for the whole world, let\u2019s be thankful for the things that matter - our health, our family\u2026 https://t.co/0kq3gDAW6I",
        "truncated": true,
        "urls": [
            {
                "expanded_url": "https://twitter.com/i/web/status/1244611003863580672",
                "url": "https://t.co/0kq3gDAW6I"
            }
        ],
        "user": {
            "id": 155659213,
            "id_str": "155659213"
        },
        "user_mentions": []
    },
    {
        "created_at": "Sat Mar 21 14:01:09 +0000 2020",
        "favorite_count": 185159,
        "hashtags": [],
        "id": 1241364225043415042,
        "id_str": "1241364225043415042",
        "lang": "en",
        "retweet_count": 15292,
        "source": "<a href=\"http://twitter.com/download/iphone\" rel=\"nofollow\">Twitter for iPhone</a>",
        "text": "If you ever dreamed of playing for millions around the world, now is your chance. Play inside, play for the world.\u2026 https://t.co/8E4pOX2BMg",
        "truncated": true,
        "urls": [
            {
                "expanded_url": "https://twitter.com/i/web/status/1241364225043415042",
                "url": "https://t.co/8E4pOX2BMg"
            }
        ],
        "user": {
            "id": 155659213,
            "id_str": "155659213"
        },
        "user_mentions": []
    },
    {
        "created_at": "Fri Mar 20 19:30:58 +0000 2020",
        "favorite_count": 122776,
        "hashtags": [],
        "id": 1241084839975059458,
        "id_str": "1241084839975059458",
        "lang": "en",
        "retweet_count": 19922,
        "source": "<a href=\"http://twitter.com/download/iphone\" rel=\"nofollow\">Twitter for iPhone</a>",
        "text": "Hi guys, just a little message and reminder of the steps we must all follow to protect ourselves and our loved ones\u2026 https://t.co/u3PXmgnZEI",
        "truncated": true,
        "urls": [
            {
                "expanded_url": "https://twitter.com/i/web/status/1241084839975059458",
                "url": "https://t.co/u3PXmgnZEI"
            }
        ],
        "user": {
            "id": 155659213,
            "id_str": "155659213"
        },
        "user_mentions": []
    }
]